windninjapy/simulation.py
windninjapy/_windninja_core.cpython-39-darwin.so
windninjapy/__init__.py
windninjapy/types.py
windninjapy/utils.py
windninjapy/.dylibs/libsnappy.1.2.2.dylib
windninjapy/.dylibs/libhwy.1.2.0.dylib
windninjapy/.dylibs/libIlmThread-3_3.32.3.3.3.dylib
windninjapy/.dylibs/libpoppler.150.0.0.dylib
windninjapy/.dylibs/libabsl_string_view.2407.0.0.dylib
windninjapy/.dylibs/libminizip.1.dylib
windninjapy/.dylibs/libabsl_hashtablez_sampler.2407.0.0.dylib
windninjapy/.dylibs/libgeos_c.1.19.2.dylib
windninjapy/.dylibs/libabsl_exponential_biased.2407.0.0.dylib
windninjapy/.dylibs/libheif.1.19.8.dylib
windninjapy/.dylibs/libxml2.2.dylib
windninjapy/.dylibs/libabsl_hash.2407.0.0.dylib
windninjapy/.dylibs/libvmaf.3.dylib
windninjapy/.dylibs/libabsl_log_internal_globals.2407.0.0.dylib
windninjapy/.dylibs/libabsl_stacktrace.2407.0.0.dylib
windninjapy/.dylibs/libOpenEXRCore-3_3.32.3.3.3.dylib
windninjapy/.dylibs/libhdf5.310.5.1.dylib
windninjapy/.dylibs/libjson-c.5.4.0.dylib
windninjapy/.dylibs/libodbcinst.2.dylib
windninjapy/.dylibs/libcom_err.3.0.dylib
windninjapy/.dylibs/libabsl_time_zone.2407.0.0.dylib
windninjapy/.dylibs/libspatialite.8.dylib
windninjapy/.dylibs/libaws-c-common.1.0.0.dylib
windninjapy/.dylibs/libclang_rt.ubsan_osx_dynamic.dylib
windninjapy/.dylibs/librttopo.1.dylib
windninjapy/.dylibs/libOpenEXRUtil-3_3.32.3.3.3.dylib
windninjapy/.dylibs/libabsl_decode_rust_punycode.2407.0.0.dylib
windninjapy/.dylibs/libkmldom.1.3.0.dylib
windninjapy/.dylibs/libabsl_log_internal_conditions.2407.0.0.dylib
windninjapy/.dylibs/libproj.25.9.6.1.dylib
windninjapy/.dylibs/libgeos.3.13.1.dylib
windninjapy/.dylibs/libpcre2-8.0.dylib
windninjapy/.dylibs/libjxl_cms.0.11.1.dylib
windninjapy/.dylibs/libabsl_flags_commandlineflag.2407.0.0.dylib
windninjapy/.dylibs/libaws-crt-cpp.dylib
windninjapy/.dylibs/liblz4.1.10.0.dylib
windninjapy/.dylibs/liburiparser.1.0.31.dylib
windninjapy-0.0.3.dist-info/RECORD
windninjapy-0.0.3.dist-info/WHEEL
windninjapy-0.0.3.dist-info/top_level.txt
windninjapy-0.0.3.dist-info/METADATA
windninjapy-0.0.3.dist-info/licenses/LICENSE
