Metadata-Version: 2.4
Name: windninjapy
Version: 0.0.3
Summary: Python bindings for the WindNinja wind simulation library
Author-email: Patrick Laflamme <patrickj.laflamme@gmail.com>
Maintainer-email: Patrick Laflamme <patrickj.laflamme@gmail.com>
License-Expression: GPL-3.0-or-later
Project-URL: Homepage, https://github.com/laflamme-fire-lab/windninjapy
Project-URL: Documentation, https://windninjapy.readthedocs.io/
Project-URL: Repository, https://github.com/laflamme-fire-lab/windninjapy.git
Project-URL: Issues, https://github.com/laflamme-fire-lab/windninjapy/issues
Project-URL: Changelog, https://github.com/laflamme-fire-lab/windninjapy/blob/main/CHANGELOG.md
Keywords: wind,simulation,meteorology,windninja,fire,modeling,terrain,atmospheric
Classifier: Development Status :: 4 - Beta
Classifier: Intended Audience :: Science/Research
Classifier: Intended Audience :: Developers
Classifier: Operating System :: OS Independent
Classifier: Programming Language :: Python :: 3
Classifier: Programming Language :: Python :: 3.9
Classifier: Programming Language :: Python :: 3.10
Classifier: Programming Language :: Python :: 3.11
Classifier: Programming Language :: Python :: 3.12
Classifier: Programming Language :: Python :: 3.13
Classifier: Programming Language :: C++
Classifier: Topic :: Scientific/Engineering :: Atmospheric Science
Classifier: Topic :: Scientific/Engineering :: Physics
Classifier: Topic :: Software Development :: Libraries :: Python Modules
Requires-Python: >=3.9
License-File: LICENSE
Requires-Dist: numpy>=1.19.0
Requires-Dist: typing-extensions>=3.7.4; python_version < "3.8"
Provides-Extra: dev
Requires-Dist: pytest>=6.0; extra == "dev"
Requires-Dist: pytest-cov>=2.10; extra == "dev"
Requires-Dist: black>=22.0; extra == "dev"
Requires-Dist: isort>=5.0; extra == "dev"
Requires-Dist: flake8>=4.0; extra == "dev"
Requires-Dist: mypy>=0.900; extra == "dev"
Requires-Dist: bump2version>=1.0; extra == "dev"
Requires-Dist: twine>=4.0; extra == "dev"
Requires-Dist: build>=0.8; extra == "dev"
Requires-Dist: check-manifest>=0.47; extra == "dev"
Provides-Extra: docs
Requires-Dist: sphinx>=4.0; extra == "docs"
Requires-Dist: sphinx-rtd-theme>=1.0; extra == "docs"
Requires-Dist: sphinx-autodoc-typehints>=1.12; extra == "docs"
Requires-Dist: myst-parser>=0.17; extra == "docs"
Provides-Extra: test
Requires-Dist: pytest>=6.0; extra == "test"
Requires-Dist: pytest-cov>=2.10; extra == "test"
Requires-Dist: pytest-mock>=3.6; extra == "test"
Requires-Dist: pytest-benchmark>=3.4; extra == "test"
Requires-Dist: pytest-rerunfailures>=10.0; extra == "test"
Dynamic: license-file
